<annotation>
	<folder>oneWay</folder>
	<filename>oneWay.jpg</filename>
	<path>C:\Users\hanna\OneDrive\Desktop\images\train\oneWay\oneWay.jpg</path>
	<source>
		<database>Unknown</database>
	</source>
	<size>
		<width>274</width>
		<height>184</height>
		<depth>3</depth>
	</size>
	<segmented>0</segmented>
	<object>
		<name>stop</name>
		<pose>Unspecified</pose>
		<truncated>0</truncated>
		<difficult>0</difficult>
		<bndbox>
			<xmin>103</xmin>
			<ymin>46</ymin>
			<xmax>154</xmax>
			<ymax>111</ymax>
		</bndbox>
	</object>
	<object>
		<name>oneWay</name>
		<pose>Unspecified</pose>
		<truncated>0</truncated>
		<difficult>0</difficult>
		<bndbox>
			<xmin>100</xmin>
			<ymin>18</ymin>
			<xmax>152</xmax>
			<ymax>56</ymax>
		</bndbox>
	</object>
</annotation>
